active_semi_clustering/__init__.py
active_semi_clustering/exceptions.py
active_semi_clustering/farthest_first_traversal.py
active_semi_clustering/active/__init__.py
active_semi_clustering/active/pairwise_constraints/__init__.py
active_semi_clustering/active/pairwise_constraints/example_oracle.py
active_semi_clustering/active/pairwise_constraints/explore_consolidate.py
active_semi_clustering/active/pairwise_constraints/helpers.py
active_semi_clustering/active/pairwise_constraints/min_max.py
active_semi_clustering/active/pairwise_constraints/npu.py
active_semi_clustering/active/pairwise_constraints/random.py
active_semi_clustering/semi_supervised/__init__.py
active_semi_clustering/semi_supervised/labeled_data/__init__.py
active_semi_clustering/semi_supervised/labeled_data/constrainedkmeans.py
active_semi_clustering/semi_supervised/labeled_data/kmeans.py
active_semi_clustering/semi_supervised/labeled_data/seededkmeans.py
active_semi_clustering/semi_supervised/pairwise_constraints/__init__.py
active_semi_clustering/semi_supervised/pairwise_constraints/constraints.py
active_semi_clustering/semi_supervised/pairwise_constraints/copkmeans.py
active_semi_clustering/semi_supervised/pairwise_constraints/mkmeans.py
active_semi_clustering/semi_supervised/pairwise_constraints/mpckmeans.py
active_semi_clustering/semi_supervised/pairwise_constraints/mpckmeansmf.py
active_semi_clustering/semi_supervised/pairwise_constraints/pckmeans.py
active_semi_clustering/semi_supervised/pairwise_constraints/rcakmeans.py
active_semi_supervised_clustering/__init__.py
active_semi_supervised_clustering/exceptions.py
active_semi_supervised_clustering/farthest_first_traversal.py
active_semi_supervised_clustering/active/__init__.py
active_semi_supervised_clustering/active/pairwise_constraints/__init__.py
active_semi_supervised_clustering/active/pairwise_constraints/explore_consolidate.py
active_semi_supervised_clustering/active/pairwise_constraints/helpers.py
active_semi_supervised_clustering-0.0.1.dist-info/METADATA
active_semi_supervised_clustering-0.0.1.dist-info/RECORD
active_semi_supervised_clustering-0.0.1.dist-info/WHEEL
active_semi_supervised_clustering-0.0.1.dist-info/top_level.txt
