Metadata-Version: 2.1
Name: active-semi-supervised-clustering
Version: 0.0.1
Summary: Active semi-supervised clustering algorithms for scikit-learn
Home-page: https://github.com/datamole-ai/active-semi-supervised-clustering
Author: Jakub Svehla
Author-email: jakub.svehla@datamole.cz
License: UNKNOWN
Platform: UNKNOWN
Classifier: Programming Language :: Python
Classifier: License :: OSI Approved :: MIT License
Classifier: Operating System :: OS Independent
Requires-Dist: numpy
Requires-Dist: scipy
Requires-Dist: scikit-learn
Requires-Dist: metric-learn (>=0.4)
